{
    "MSI": "em ét ai",
    "NSX": "nhà sản xuất",
    "LCK": "eo si cây",
    "LPL": "eo pi eo",
    "JD": "gi đi",
    "TOP": "tốp",
    "LMHT": "liên minh huyền thoại",
    "HLV": "huấn luyện viên",
    "VND": "việt nam đồng",
    "PK": "pê ca",
    "FREE": "phờ ri",
    "NPH": "nhà phát hành",
    "SS": "ét ét",
    "SSS": "ét ét ét",
    "NPC": "en pi si",
    "VNĐ": "việt nam đồng",
    "FBI": "ép bi ai",
    "MXH": "mạng xã hội",
    "RGB": "a gi bi",
    "PC": "pi si",
    "RPG": "a pi gi",
    "FIFA": "phi pha",
    "GB": "gờ bê",
    "RAM": "ram",
    "HD": "hát đê",
    "FPS": "ép pê ét",
    "PUBG": "pắp gi",
    "VN": "việt nam",
    "USD": "iu ét đi",
    "SEA": "xi",
    "MC": "em si",
    "VCS": "vi si ét",
    "BLV": "bình luận viên",
    "CS": "si ét",
    "GO": "gâu",
    "D": "đi",
    "IQ": "i quy",
    "MMORPG": "em em âu a pi gi",
    "BQT": "bê quy tê",
    "AFK": "a ép ca",
    "DOTA": "đô ta",
    "JX": "gi ích",
    "MVP": "em vi pi",
    "HP": "hát pê",
    "PBE": "pê bê e",
    "MOBA": "mô ba",
    "SSD": "ét ét đi",
    "CPU": "xê pê u",
    "AMD": "a mờ đê",
    "HDD": "hát đê đê",
    "GPU": "gờ pê u",
    "NVIDIA": "en vi đi a",
    "USB": "iu ét bi",
    "ELO": "ê lô",
    "BXH": "bảng xếp hạng",
    "ĐTDV": "đội tuyển danh vọng",
    "IP": "ai pi",
    "COVID": "cô vít",
    "LED": "lét",
    "PS": "pi ét",
    "HOT": "hót",
    "GTA": "gờ tê a",
    "AAA": "tríp pồ ây",
    "GAM": "gam",
    "AV": "ây vi",
    "CKTG": "chung kết thế giới",
    "CEO": "si i âu",
    "TV": "ti vi",
    "VNG": "vi en gi",
    "SKT": "ét cây ti",
    "EVOS": "e vốt",
    "LEC": "eo i si",
    "SMPT": "sức mạnh phép thuật",
    "MV": "em vi",
    "GTX": "gờ tê ích",
    "VIP": "víp",
    "MCU": "em si iu",
    "DC": "đi si",
    "SMCK": "sức mạnh công kích",
    "AI": "ây ai",
    "FL": "phờ lát",
    "FPX": "ép pê ích",
    "NASA": "na sa",
    "PCS": "pi si ét",
    "ADC": "a đê xê",
    "BTC": "ban tổ chức",
    "DNA": "đi en ây",
    "AD": "a đê",
    "LCS": "eo si ét",
    "ĐTCL": "đấu trường chân lý",
    "CGI": "si gi ai",
    "NTN": "nờ tê nờ",
    "SSM": "ét ét mờ",
    "TVB": "ti vi bi",
    "WHO": "vê kép hát ô",
    "BBC": "bi bi si",
    "CNN": "si en en",
    "MU": "em iu",
    "HIV": "hát i vê",
    "ICT": "ai ci ti",
    "PBR": "pi bi a",
    "KCDC": "cây si đi si",
    "AWC": "a vê kép xê",
    "GCS": "gi si ét",
    "AIC": "ây ai si",
    "F A": "ép a",
    "ESL": "i ét eo",
    "IEM": "i em mờ",
    "VTC": "vê tê xê",
    "DAMWON": "dam guôn",
    "FA": "ép a",
    "NDT": "nhân dân tệ",
    "VR": "vi a",
    "CD": "si đi si",
    "AOG": "ây âu gi",
    "APK": "ây pi cây",
    "SARS": "sát",
    "AP": "a pê",
    "MARVEL": "ma vồ",
    "KOL": "cây ô eo",
    "LAN": "lan",
    "HLTV": "hát lờ tê vê",
    "AWP": "ốp",
    "BLAST": "bờ lát",
    "IGL": "i gờ lờ",
    "TP": "thành phố",
    "HCM": "hồ chí minh",
    "EG": "e gờ",
    "PR": "pi a",
    "UBND": "uỷ ban nhân dân",
    "FTV": "ép tê vê",
    "KT": "cây ti",
    "RPL": "a pi eo",
    "IOS": "ai ô ét",
    "DLC": "đi eo si",
    "KNB": "kim nguyên bảo",
    "ESPN": "i ét pi en",
    "OF": "ọp",
    "OP": "âu pi",
    "CDC": "si đi si",
    "IV": "bốn",
    "ARK": "a rờ ca",
    "VLTK": "võ lâm truyền kỳ",
    "PES": "pét",
    "VGA": "vê gờ a",
    "SLG": "ét lờ gờ",
    "THE": "dơ",
    "KDA": "ca dê a",
    "SAO": "sao",
    "IG": "i gờ",
    "SBTC": "ét bi ti si",
    "SNK": "ét en cây",
    "APL": "ây pi eo",
    "PV": "phóng viên",
    "SN": "ét nờ",
    "LNG": "lờ nờ gờ",
    "VALORANT": "va lo ran",
    "RTX": "a ti ích",
    "FFQ": "ép ép quy",
    "LMS": "lờ mờ ét",
    "SK": "ét cây",
    "RNG": "a en gi",
    "FNC": "phờ na tích",
    "MMO": "em em âu",
    "ONE": "goăn",
    "AHQ": "a hát quy",
    "MEGA": "mê ga",
    "DNK": "đi en cây",
    "LK": "eo cây",
    "URF": "u rờ ép",
    "CH": "xê hát",
    "PVP": "pi vi pi",
    "CG": "si gi",
    "ĐKVĐ": "đương kim vô địch",
    "DWG": "đam guôn gêm ming",
    "HKA": "hát ka a",
    "EU": "ê u",
    "AR": "a rờ",
    "AOE": "a o e",
    "SANDBOX": "san bóc",
    "VTV": "vê tê vê",
    "PMPL": "pi em pi eo",
    "IMAX": "ai mắc",
    "CLICK": "cờ lích",
    "SE": "ét e",
    "SGB": "ét bi gi",
    "KIA": "ki a",
    "DK": "đi cây",
    "MAD": "mát",
    "EGO": "ê gô",
    "CES": "sét",
    "TS": "ti ét",
    "SGP": "ét gờ pê",
    "AOV": "a ô vê",
    "WONDER": "guôn đơ",
    "WOMAN": "guôn mừn",
    "GOG": "gi ô gi",
    "POPS": "póp",
    "AS": "a ét",
    "PVB": "pi vi bi",
    "FB": "phây búc",
    "MOBILE": "mô bi",
    "HH": "hát hát",
    "SSLELBCD HM YTT": "ét ét lờ e lờ bê xê dê hát mờ i tê tê",
    "FW": "phờ lát gúup",
    "BO": "bo",
    "VETV": "vê e tê vê",
    "TL": "tim li quít",
    "MP": "mờ pê",
    "PMCO": "pi em si âu",
    "SMILE": "sờ mai",
    "SGD": "sở giáo dục",
    "BOX": "bóc",
    "LGD": "eo gi đi",
    "V": "vê",
    "DA": "đi ây",
    "TES": "tét",
    "JDG": "giây đi gi",
    "PSG": "pi ét gi",
    "CĐM": "cộng đồng mạng",
    "QQ": "quy quy",
    "B F": "bê ép",
    "CLB": "câu lạc bộ",
    "THPT": "trung học phổ thông",
    "DRX": "đi a ích",
    "TB": "tê ta bai",
    "ĐH": "đại học",
    "SBS": "ét bê ét",
    "DBL": "đi bi eo",
    "TPE": "tê pê e",
    "TI": "ti ai",
    "VEC": "vi ê si",
    "DJ": "đi giây",
    "GAME": "gêm",
    "TSM": "ti ét em",
    "IGP": "ai gi pi",
    "ROG": "róc",
    "TVA": "ti vi ây",
    "CP": "xê pê",
    "DCEU": "đi si e u",
    "HBO": "hát bê ô",
    "GODZILLA": "gót di la",
    "VS": "vơ sút",
    "KONG": "công",
    "IGN": "i gờ nờ",
    "QTV": "quy ti vi",
    "ASUS": "a sớt",
    "HDMI": "hát đê mờ i",
    "IPS": "ai pi ét",
    "ROM": "rom",
    "MSP": "em ét pi",
    "CGV": "si gi vi",
    "TCG": "tê xê gờ",
    "DPS": "đi pi ét",
    "SSR": "ét ét rờ",
    "CDN": "si đi en",
    "EXP": "e ích pi",
    "BV": "bệnh viện",
    "TPHCM": "thành phố hồ chí minh",
    "VGM": "vê gờ mờ",
    "XB": "ích bê",
    "SMG": "ét em gi",
    "JRPG": "gi a pi gi",
    "RNA": "a en ây",
    "TT": "thể thao",
    "VH": "văn hóa",
    "ACE": "ây",
    "BN": "bệnh nhân",
    "NES": "nét",
    "DOOM": "doom",
    "PGS": "phó giáo sư",
    "RX": "rờ ích",
    "TF": "tê ép",
    "RDNA": "a đi en ây",
    "CIA": "si ai ây",
    "TƯ": "trung ương",
    "RE": "rờ e",
    "RP": "rờ pê",
    "SARS COV": "sát   cô vi",
    "FPL": "ép pi eo",
    "SATA": "sa ta",
    "MERS": "mơ",
    "PCR": "pi xi a",
    "FPT": "ép pi ti",
    "OG": "âu gi",
    "AC": "a sa sin cờ rít",
    "HĐH": "hệ điều hành",
    "VRAM": "vi ram",
    "ICM": "ai si em",
    "BIG": "bích",
    "ARPG": "ây a pi gi",
    "ARAM": "a ram",
    "WD": "vê kép đê",
    "TP HCM": "thành phố hồ chí minh",
    "BCĐ": "ban chỉ đạo",
    "ME": "mi",
    "ETH": "e thơ ri um",
    "IRL": "in riu lai",
    "YC": "goai si",
    "XS": "ích ét",
    "GDC": "gi đi si",
    "SP": "súp pót",
    "IT": "ít",
    "HCV": "huy chương vàng",
    "WPF": "vê kép pê ép",
    "FAM": "pham",
    "SOLDIER": "sâu dờ",
    "OK": "ô kê",
    "HDR": "hát đê rờ",
    "QG": "quy gi",
    "OLED": "ô lét",
    "MJ": "em giây",
    "KZ": "ca dét",
    "VPN": "vi pi en",
    "LONGMO": "long mô"
}